setup.py
javoo_dsnd_probability/Binomialdistribution.py
javoo_dsnd_probability/Gaussiandistribution.py
javoo_dsnd_probability/Generaldistribution.py
javoo_dsnd_probability/__init__.py
javoo_dsnd_probability.egg-info/PKG-INFO
javoo_dsnd_probability.egg-info/SOURCES.txt
javoo_dsnd_probability.egg-info/dependency_links.txt
javoo_dsnd_probability.egg-info/not-zip-safe
javoo_dsnd_probability.egg-info/top_level.txt