Metadata-Version: 2.1
Name: javoo-dsnd-probability
Version: 1.0
Summary: Gaussian and Binomial distributions
Home-page: UNKNOWN
Author: Andrew Paster - Javoo
Author-email: javoo.code.ando@gmail.com
License: UNKNOWN
Platform: UNKNOWN
